extended_chart/ExtendedChart.py
extended_chart/RenderStrategyChart.py
extended_chart/__init__.py
extended_chart/add_background_span.py
extended_chart/add_histogram.py
extended_chart/add_marker.py
extended_chart/add_overlay.py
extended_chart/add_support_lines.py
extended_chart/add_table.py
extended_chart/add_trade_marker.py
extended_chart/add_trendline.py
extended_chart/style.py
extended_chart/utils/color_converter.py
extended_chart/utils/rename_columns.py
extended_chart-0.4.3.11.dist-info/METADATA
extended_chart-0.4.3.11.dist-info/WHEEL
extended_chart-0.4.3.11.dist-info/top_level.txt
extended_chart-0.4.3.11.dist-info/RECORD
