Metadata-Version: 2.1
Name: extended-chart
Version: 0.4.3.11
Summary: wrapper for lightweight-charts-python for trading strategy discovery
Home-page: https://github.com/karunkrishna/extended_chart
Author: Karun Krishna
Author-email: karun.krishna@gmail.com
License: MIT
Requires-Dist: pywebview (==4.4.1)
Requires-Dist: lightweight-charts (==1.0.18.9)
